codeforlife/__init__.py
codeforlife/_test.py
codeforlife/auth.py
codeforlife/caches.py
codeforlife/filters.py
codeforlife/forms.py
codeforlife/logging.py
codeforlife/mail.py
codeforlife/pagination.py
codeforlife/py.typed
codeforlife/response.py
codeforlife/routers.py
codeforlife/server.py
codeforlife/types.py
codeforlife/commands/__init__.py
codeforlife/commands/load_fixtures.py
codeforlife/commands/summarize_fixtures.py
codeforlife/data/.gitkeep
codeforlife/middlewares/__init__.py
codeforlife/middlewares/session.py
codeforlife/models/__init__.py
codeforlife/models/abstract_base_session.py
codeforlife/models/abstract_base_user.py
codeforlife/models/base.py
codeforlife/models/base_session_store.py
codeforlife/models/encrypted_char_field.py
codeforlife/models/signals/__init__.py
codeforlife/models/signals/general.py
codeforlife/models/signals/post_save.py
codeforlife/models/signals/pre_save.py
codeforlife/models/signals/receiver.py
codeforlife/permissions/__init__.py
codeforlife/permissions/allow_any.py
codeforlife/permissions/allow_none.py
codeforlife/permissions/auth_header_is_github_oidc_token.py
codeforlife/permissions/auth_header_is_github_oidc_token_test.py
codeforlife/permissions/base.py
codeforlife/permissions/is_authenticated.py
codeforlife/permissions/operators.py
codeforlife/request/__init__.py
codeforlife/request/drf.py
codeforlife/request/http.py
codeforlife/request/wsgi.py
codeforlife/serializers/__init__.py
codeforlife/serializers/base.py
codeforlife/serializers/model.py
codeforlife/serializers/model_list.py
codeforlife/settings/__init__.py
codeforlife/settings/custom.py
codeforlife/settings/django.py
codeforlife/settings/otp.py
codeforlife/settings/third_party.py
codeforlife/tasks/__init__.py
codeforlife/tasks/bigquery.py
codeforlife/tasks/bigquery_test.py
codeforlife/tasks/utils.py
codeforlife/templates/codeforlife/rest_framework/api.html
codeforlife/tests/__init__.py
codeforlife/tests/api.py
codeforlife/tests/api_client.py
codeforlife-0.31.1.dist-info/licenses/LICENSE.md
codeforlife-0.31.1.dist-info/METADATA
codeforlife-0.31.1.dist-info/WHEEL
codeforlife-0.31.1.dist-info/top_level.txt
codeforlife-0.31.1.dist-info/RECORD
